denki_client-0.2.0.dist-info/METADATA
denki_client-0.2.0.dist-info/WHEEL
denki_client-0.2.0.dist-info/licenses/LICENSE
denki_client/__init__.py
denki_client/_core.pyd
denki_client/_core.pyi
denki_client/area.py
denki_client/entsoe.py
denki_client/exceptions.py
denki_client/parsers.py
denki_client/schemas.py
denki_client/utils.py
denki_client-0.2.0.dist-info/RECORD
