Metadata-Version: 2.4
Name: denki-client
Version: 0.2.0
Requires-Dist: httpx>=0.28.1
Requires-Dist: narwhals>=1.39.0
Requires-Dist: python-dateutil>=2.9.0.post0
Requires-Dist: pytz>=2025.2
Requires-Dist: tenacity>=9.1.2
License-File: LICENSE
License-File: LICENSE
Summary: Agnostic client for ENTSO-e API.
Home-Page: https://github.com/Tijoxa/denki-client
Author-email: Tijoxa <92037181+Tijoxa@users.noreply.github.com>
Requires-Python: >=3.12
